flask_restone.py
flask_restone-0.3.0.dist-info/LICENSE
flask_restone-0.3.0.dist-info/METADATA
flask_restone-0.3.0.dist-info/WHEEL
flask_restone-0.3.0.dist-info/top_level.txt
flask_restone-0.3.0.dist-info/RECORD
