Metadata-Version: 2.1
Name: flask_restone
Version: 0.3.0
Summary: All in one framework for creating RESTful APIs
Author-email: Arry Lee <arry_lee@qq.com>
Project-URL: Homepage, https://github.com/flask-restone/flask-restone
Project-URL: Bug Tracker, https://github.com/flask-restone/flask-restone/issues
Classifier: Programming Language :: Python :: 3
Classifier: License :: OSI Approved :: MIT License
Classifier: Operating System :: OS Independent
Requires-Python: >=3.5
License-File: LICENSE
